[{"financial_year":2002,"total_plastics_collected":25334.11,"total_plastics_recycled":24025.48,"not_recycled_plastics":1308.63},{"financial_year":2003,"total_plastics_collected":29830.03,"total_plastics_recycled":29415.91,"not_recycled_plastics":414.12},{"financial_year":2004,"total_plastics_collected":24311.31,"total_plastics_recycled":23079.14,"not_recycled_plastics":1232.17},{"financial_year":2005,"total_plastics_collected":22246.87,"total_plastics_recycled":19365.84,"not_recycled_plastics":2881.03},{"financial_year":2006,"total_plastics_collected":29108.09,"total_plastics_recycled":28518.605,"not_recycled_plastics":589.485},{"financial_year":2007,"total_plastics_collected":36262.01,"total_plastics_recycled":31110.36,"not_recycled_plastics":5151.65},{"financial_year":2008,"total_plastics_collected":42873.639,"total_plastics_recycled":32486.996,"not_recycled_plastics":10386.643},{"financial_year":2009,"total_plastics_collected":35574.544,"total_plastics_recycled":35245.621,"not_recycled_plastics":328.923},{"financial_year":2010,"total_plastics_collected":38429.168,"total_plastics_recycled":37738.122,"not_recycled_plastics":691.046},{"financial_year":2011,"total_plastics_collected":41919.276,"total_plastics_recycled":40905.856,"not_recycled_plastics":1013.42},{"financial_year":2012,"total_plastics_collected":37971.16,"total_plastics_recycled":37039.88,"not_recycled_plastics":931.28},{"financial_year":2013,"total_plastics_collected":43250.65,"total_plastics_recycled":42460.36,"not_recycled_plastics":790.29},{"financial_year":2014,"total_plastics_collected":35417.8564,"total_plastics_recycled":34665.8266,"not_recycled_plastics":752.0298},{"financial_year":2015,"total_plastics_collected":39425.035,"total_plastics_recycled":38427.64,"not_recycled_plastics":997.395},{"financial_year":2016,"total_plastics_collected":37687.82,"total_plastics_recycled":36803,"not_recycled_plastics":884.82},{"financial_year":2017,"total_plastics_collected":35467.62,"total_plastics_recycled":34509.858,"not_recycled_plastics":957.762},{"financial_year":2018,"total_plastics_collected":49948.69,"total_plastics_recycled":49556.81,"not_recycled_plastics":391.88},{"financial_year":2019,"total_plastics_collected":30800.14,"total_plastics_recycled":29651.4,"not_recycled_plastics":1148.74},{"financial_year":2020,"total_plastics_collected":36505.776,"total_plastics_recycled":36267.026,"not_recycled_plastics":238.75},{"financial_year":2021,"total_plastics_collected":32224.95,"total_plastics_recycled":28789.73,"not_recycled_plastics":3435.22}]
